LICENSE
MANIFEST.in
setup.py
tag_processor/__init__.py
tag_processor/main.py
tag_processor/models.py
tag_processor/services.py
tag_processor.egg-info/PKG-INFO
tag_processor.egg-info/SOURCES.txt
tag_processor.egg-info/dependency_links.txt
tag_processor.egg-info/top_level.txt
tag_processor/tests/__init__.py
tag_processor/tests/test_datacontainer.py
tag_processor/tests/test_parser.py
tag_processor/tests/test_processor.py