Metadata-Version: 1.1
Name: tag-processor
Version: 0.3.0
Summary: Application for processing tags inside string, like ${tag}
Home-page: https://bitbucket.org/creekmind/tag_processor/
Author: Petr Kapsamun
Author-email: creekmind@gmail.com
License: BSD
Platform: UNKNOWN
Classifier: Intended Audience :: Developers
Classifier: Operating System :: OS Independent
Classifier: Programming Language :: Python
Classifier: Programming Language :: Python :: 2
Classifier: Programming Language :: Python :: 2.7
Classifier: Programming Language :: Python :: 3.4
